opentelemetry/instrumentation/kafka/__init__.py
opentelemetry/instrumentation/kafka/package.py
opentelemetry/instrumentation/kafka/utils.py
opentelemetry/instrumentation/kafka/version.py
opentelemetry_instrumentation_kafka_python-0.60b1.dist-info/METADATA
opentelemetry_instrumentation_kafka_python-0.60b1.dist-info/WHEEL
opentelemetry_instrumentation_kafka_python-0.60b1.dist-info/entry_points.txt
opentelemetry_instrumentation_kafka_python-0.60b1.dist-info/licenses/LICENSE
opentelemetry_instrumentation_kafka_python-0.60b1.dist-info/RECORD
